{
  "date": "2026-04-26",
  "generatedAt": "2026-04-26T07:09:42.420016",
  "stage": "incremental",
  "comparison": {
    "todayDate": "2026-04-26",
    "yesterdayDate": "2026-04-25",
    "yesterdayExists": true
  },
  "results": [
    {
      "siteId": "mnr_gov_cn",
      "siteName": "自然资源部",
      "url": "http://www.mnr.gov.cn/",
      "status": "success",
      "announcements": [
        {
          "title": "习近平：把“义乌发展经验”进一步总结好...",
          "url": "https://www.gov.cn/yaowen/liebiao/202604/content_7066680.htm",
          "date": ""
        },
        {
          "title": "习近平同佛得角总统内韦斯就中佛建交50周...",
          "url": "https://www.gov.cn/yaowen/liebiao/202604/content_7066968.htm",
          "date": ""
        },
        {
          "title": "李强主持召开国务院常务会议 研究科技创新...",
          "url": "https://www.gov.cn/yaowen/liebiao/202604/content_7066881.htm",
          "date": ""
        },
        {
          "title": "自然资源部召开全国汛期地灾防治工作视频会议",
          "url": "http://www.mnr.gov.cn/dt/ywbb/202604/t20260425_2927945.html",
          "date": ""
        }
      ],
      "newCount": 4
    },
    {
      "siteId": "kjt_fujian_gov_cn",
      "siteName": "福建省科学技术厅",
      "url": "http://kjt.fujian.gov.cn/",
      "status": "success",
      "announcements": [
        {
          "title": "省委一季度工作会议在榕召开",
          "url": "http://www.fujian.gov.cn/xwdt/fjyw/202604/t20260425_7131243.htm",
          "date": "2026-04-25"
        },
        {
          "title": "赵龙调研公安司法信访工作",
          "url": "http://www.fujian.gov.cn/xwdt/fjyw/202604/t20260425_7131244.htm",
          "date": "2026-04-25"
        },
        {
          "title": "中央和国家机关青年来闽支教帮扶工作座谈交流会召开",
          "url": "http://www.fujian.gov.cn/xwdt/fjyw/202604/t20260425_7131246.htm",
          "date": "2026-04-25"
        },
        {
          "title": "省委政法委员会召开2026年第四次全体会议",
          "url": "http://www.fujian.gov.cn/xwdt/fjyw/202604/t20260425_7131247.htm",
          "date": "2026-04-25"
        },
        {
          "title": "省政协重点提案办理协调会召开",
          "url": "http://www.fujian.gov.cn/xwdt/fjyw/202604/t20260425_7131248.htm",
          "date": "2026-04-25"
        }
      ],
      "newCount": 5
    },
    {
      "siteId": "gxt_fujian_gov_cn",
      "siteName": "福建省供销合作社",
      "url": "http://gxt.fujian.gov.cn/",
      "status": "success",
      "announcements": [
        {
          "title": "省委一季度工作会议在榕召开",
          "url": "http://www.fujian.gov.cn/xwdt/fjyw/202604/t20260425_7131243.htm",
          "date": "2026-04-25"
        },
        {
          "title": "赵龙调研公安司法信访工作",
          "url": "http://www.fujian.gov.cn/xwdt/fjyw/202604/t20260425_7131244.htm",
          "date": "2026-04-25"
        },
        {
          "title": "中央和国家机关青年来闽支教帮扶工作座谈交流会召开",
          "url": "http://www.fujian.gov.cn/xwdt/fjyw/202604/t20260425_7131246.htm",
          "date": "2026-04-25"
        },
        {
          "title": "省委政法委员会召开2026年第四次全体会议",
          "url": "http://www.fujian.gov.cn/xwdt/fjyw/202604/t20260425_7131247.htm",
          "date": "2026-04-25"
        },
        {
          "title": "省政协重点提案办理协调会召开",
          "url": "http://www.fujian.gov.cn/xwdt/fjyw/202604/t20260425_7131248.htm",
          "date": "2026-04-25"
        },
        {
          "title": "5.1%背后的福建经济底色",
          "url": "http://www.fujian.gov.cn/xwdt/fjyw/202604/t20260425_7131249.htm",
          "date": "2026-04-25"
        }
      ],
      "newCount": 6
    }
  ],
  "summary": {
    "sitesWithNew": 3,
    "totalNewAnnouncements": 15
  }
}