[
  {
    "id": "http://sti.xm.gov.cn/xxgk/gzdt/202603/t20260316_2985712.htm",
    "title": "市科技局召开树立和践行正确政绩观学习教育动员部署会",
    "url": "http://sti.xm.gov.cn/xxgk/gzdt/202603/t20260316_2985712.htm",
    "date": "2026-03-16",
    "siteId": "sti_xm_gov_cn",
    "siteName": "厦门市科学技术局",
    "siteUrl": "http://sti.xm.gov.cn/",
    "category": "厦门市",
    "summary": ""
  },
  {
    "id": "http://kgxj.haikou.gov.cn/202603/t1515514.shtml",
    "title": "海口市科学技术和工业信息化局关于公开征求开展树立和践行正确政绩观 学习教育意见...",
    "url": "http://kgxj.haikou.gov.cn/202603/t1515514.shtml",
    "date": "2026-03-16",
    "siteId": "kgxj_haikou_gov_cn",
    "siteName": "海口市科学技术和工业信息化局",
    "siteUrl": "http://kgxj.haikou.gov.cn/zfxxgk/gsgg/",
    "category": "国家",
    "summary": ""
  },
  {
    "id": "http://jyt.fujian.gov.cn/202603/t20260316_7110842.htm",
    "title": "关于教育部“最美高校辅导员”“最美大学生”推选展示活动拟推荐人选的公示",
    "url": "http://jyt.fujian.gov.cn/202603/t20260316_7110842.htm",
    "date": "2026-03-16",
    "siteId": "jyt_fujian_gov_cn",
    "siteName": "福建省教育厅",
    "siteUrl": "http://jyt.fujian.gov.cn/xxgk/gggs/",
    "category": "福建省",
    "summary": ""
  }
]