{
  "date": "2026-03-16",
  "site_id": "fgw_fujian_gov_cn",
  "site_name": "福建省发改委",
  "total": 129,
  "announcements": [
    {
      "title": "代表委员之声",
      "url": "http://fgw.fujian.gov.cn/zwgk/gsgg/dbwyzs/",
      "site_id": "fgw_fujian_gov_cn",
      "site_name": "福建省发改委",
      "publish_date": null,
      "crawl_date": "2026-03-16"
    },
    {
      "title": "领导活动信息",
      "url": "http://fgw.fujian.gov.cn/zwgk/gsgg/ldhdxx/",
      "site_id": "fgw_fujian_gov_cn",
      "site_name": "福建省发改委",
      "publish_date": null,
      "crawl_date": "2026-03-16"
    },
    {
      "title": "福建省发展和改革委员会及下属单位综合性涉企收费目录清单",
      "url": "http://fgw.fujian.gov.cn/202506/t20250630_6959288.htm",
      "site_id": "fgw_fujian_gov_cn",
      "site_name": "福建省发改委",
      "publish_date": null,
      "crawl_date": "2026-03-16"
    },
    {
      "title": "福建省发展和改革委员会关于成品油价格调整的通告",
      "url": "http://fgw.fujian.gov.cn/zwgk/gsgg/../zfxxgkzl/zfxxgkml/yzdgkdqtxx/202603/t20260309_7107766.htm",
      "site_id": "fgw_fujian_gov_cn",
      "site_name": "福建省发改委",
      "publish_date": null,
      "crawl_date": "2026-03-16"
    },
    {
      "title": "福建省发展和改革委员会 福建省新闻出版局关于公布我省2026年春季中小学教材和教辅材料零售价格的通告",
      "url": "http://fgw.fujian.gov.cn/zwgk/gsgg/../zfxxgkzl/zfxxgkml/fpjyylsbjy/202603/t20260306_7106207.htm",
      "site_id": "fgw_fujian_gov_cn",
      "site_name": "福建省发改委",
      "publish_date": null,
      "crawl_date": "2026-03-16"
    },
    {
      "title": "福建省发展和改革委员会关于2025年度省重点项目考评结果的通报",
      "url": "http://fgw.fujian.gov.cn/zwgk/gsgg/../zfxxgkzl/zfxxgkml/yzdgkdqtxx/202603/t20260302_7103687.htm",
      "site_id": "fgw_fujian_gov_cn",
      "site_name": "福建省发改委",
      "publish_date": null,
      "crawl_date": "2026-03-16"
    },
    {
      "title": "福建省发展和改革委员会关于成品油价格调整的通告",
      "url": "http://fgw.fujian.gov.cn/zwgk/gsgg/../zfxxgkzl/zfxxgkml/yzdgkdqtxx/202602/t20260224_7100324.htm",
      "site_id": "fgw_fujian_gov_cn",
      "site_name": "福建省发改委",
      "publish_date": null,
      "crawl_date": "2026-03-16"
    },
    {
      "title": "福建省发展和改革委员会“双随机、一公开”年度抽查计划",
      "url": "http://fgw.fujian.gov.cn/zwgk/gsgg/../ztzl/jgzf/ssjygk/202602/t20260212_7092794.htm",
      "site_id": "fgw_fujian_gov_cn",
      "site_name": "福建省发改委",
      "publish_date": null,
      "crawl_date": "2026-03-16"
    },
    {
      "title": "福建省发展和改革委员会关于公布2026年度省重点项目名单的通知",
      "url": "http://fgw.fujian.gov.cn/zwgk/gsgg/../zfxxgkzl/zfxxgkml/zdjsxmpzhss/202602/t20260206_7090452.htm",
      "site_id": "fgw_fujian_gov_cn",
      "site_name": "福建省发改委",
      "publish_date": null,
      "crawl_date": "2026-03-16"
    },
    {
      "title": "福建省发展和改革委员会关于成品油价格调整的通告",
      "url": "http://fgw.fujian.gov.cn/zwgk/gsgg/../zfxxgkzl/zfxxgkml/yzdgkdqtxx/202602/t20260203_7088713.htm",
      "site_id": "fgw_fujian_gov_cn",
      "site_name": "福建省发改委",
      "publish_date": null,
      "crawl_date": "2026-03-16"
    },
    {
      "title": "2025年度省重点项目拟考评为较好和A级单位公示",
      "url": "http://fgw.fujian.gov.cn/202602/t20260203_7088588.htm",
      "site_id": "fgw_fujian_gov_cn",
      "site_name": "福建省发改委",
      "publish_date": null,
      "crawl_date": "2026-03-16"
    },
    {
      "title": "福建省发展和改革委员会关于成品油价格调整的通告",
      "url": "http://fgw.fujian.gov.cn/zwgk/gsgg/../zfxxgkzl/zfxxgkml/yzdgkdqtxx/202601/t20260120_7083070.htm",
      "site_id": "fgw_fujian_gov_cn",
      "site_name": "福建省发改委",
      "publish_date": null,
      "crawl_date": "2026-03-16"
    },
    {
      "title": "2025年度我委行政处罚信息情况",
      "url": "http://fgw.fujian.gov.cn/202601/t20260107_7072295.htm",
      "site_id": "fgw_fujian_gov_cn",
      "site_name": "福建省发改委",
      "publish_date": null,
      "crawl_date": "2026-03-16"
    },
    {
      "title": "福建省发展和改革委员会门户网站年度报表（2025年度）",
      "url": "http://fgw.fujian.gov.cn/202601/P020260108349332808021.pdf",
      "site_id": "fgw_fujian_gov_cn",
      "site_name": "福建省发改委",
      "publish_date": null,
      "crawl_date": "2026-03-16"
    },
    {
      "title": "福建省发展和改革委员会“双随机、一公开”抽查情况公示",
      "url": "http://fgw.fujian.gov.cn/zwgk/gsgg/../ztzl/jgzf/ssjygk/202512/t20251226_7061385.htm",
      "site_id": "fgw_fujian_gov_cn",
      "site_name": "福建省发改委",
      "publish_date": null,
      "crawl_date": "2026-03-16"
    },
    {
      "title": "福建省发展和改革委员会“双随机、一公开”抽查情况公示",
      "url": "http://fgw.fujian.gov.cn/zwgk/gsgg/../ztzl/jgzf/ssjygk/202512/t20251223_7049373.htm",
      "site_id": "fgw_fujian_gov_cn",
      "site_name": "福建省发改委",
      "publish_date": null,
      "crawl_date": "2026-03-16"
    },
    {
      "title": "福建省发展和改革委员会关于成品油价格调整的通告",
      "url": "http://fgw.fujian.gov.cn/zwgk/gsgg/../zfxxgkzl/zfxxgkml/yzdgkdqtxx/202512/t20251222_7049242.htm",
      "site_id": "fgw_fujian_gov_cn",
      "site_name": "福建省发改委",
      "publish_date": null,
      "crawl_date": "2026-03-16"
    },
    {
      "title": "福建省发展和改革委员会“双随机、一公开”抽查情况公示",
      "url": "http://fgw.fujian.gov.cn/zwgk/gsgg/../ztzl/jgzf/ssjygk/202512/t20251219_7048470.htm",
      "site_id": "fgw_fujian_gov_cn",
      "site_name": "福建省发改委",
      "publish_date": null,
      "crawl_date": "2026-03-16"
    },
    {
      "title": "福建省发展和改革委员会“双随机、一公开”抽查情况公示",
      "url": "http://fgw.fujian.gov.cn/zwgk/gsgg/../ztzl/jgzf/ssjygk/202512/t20251218_7047989.htm",
      "site_id": "fgw_fujian_gov_cn",
      "site_name": "福建省发改委",
      "publish_date": null,
      "crawl_date": "2026-03-16"
    },
    {
      "title": "询价结果公告",
      "url": "http://fgw.fujian.gov.cn/202512/t20251216_7046948.htm",
      "site_id": "fgw_fujian_gov_cn",
      "site_name": "福建省发改委",
      "publish_date": null,
      "crawl_date": "2026-03-16"
    },
    {
      "title": "2025政务数据及电子证照质量“双随机、一公开”抽查情况公示（第二批）",
      "url": "http://fgw.fujian.gov.cn/zwgk/gsgg/../ztzl/jgzf/ssjygk/202512/t20251211_7044953.htm",
      "site_id": "fgw_fujian_gov_cn",
      "site_name": "福建省发改委",
      "publish_date": null,
      "crawl_date": "2026-03-16"
    },
    {
      "title": "2025政务数据及电子证照质量“双随机、一公开”抽查情况公示（第一批）",
      "url": "http://fgw.fujian.gov.cn/zwgk/gsgg/../ztzl/jgzf/ssjygk/202512/t20251211_7044946.htm",
      "site_id": "fgw_fujian_gov_cn",
      "site_name": "福建省发改委",
      "publish_date": null,
      "crawl_date": "2026-03-16"
    },
    {
      "title": "福建省数据管理局关于2025年福建省信息技术应用创新解决方案入选项目的公示",
      "url": "http://fgw.fujian.gov.cn/202512/t20251210_7044696.htm",
      "site_id": "fgw_fujian_gov_cn",
      "site_name": "福建省发改委",
      "publish_date": null,
      "crawl_date": "2026-03-16"
    },
    {
      "title": "福建省发展和改革委员会“双随机、一公开”抽查情况公示",
      "url": "http://fgw.fujian.gov.cn/zwgk/gsgg/../ztzl/jgzf/ssjygk/202512/t20251209_7044038.htm",
      "site_id": "fgw_fujian_gov_cn",
      "site_name": "福建省发改委",
      "publish_date": null,
      "crawl_date": "2026-03-16"
    },
    {
      "title": "福建省发展和改革委员会关于成品油价格调整的通告",
      "url": "http://fgw.fujian.gov.cn/zwgk/gsgg/../zfxxgkzl/zfxxgkml/yzdgkdqtxx/202512/t20251208_7043938.htm",
      "site_id": "fgw_fujian_gov_cn",
      "site_name": "福建省发改委",
      "publish_date": null,
      "crawl_date": "2026-03-16"
    },
    {
      "title": "关于全国价格工作先进集体和先进个人推荐对象的公示",
      "url": "http://fgw.fujian.gov.cn/202512/t20251205_7042651.htm",
      "site_id": "fgw_fujian_gov_cn",
      "site_name": "福建省发改委",
      "publish_date": null,
      "crawl_date": "2026-03-16"
    },
    {
      "title": "福建省发展和改革委员会“双随机、一公开”抽查情况公示",
      "url": "http://fgw.fujian.gov.cn/zwgk/gsgg/../ztzl/jgzf/ssjygk/202512/t20251201_7041019.htm",
      "site_id": "fgw_fujian_gov_cn",
      "site_name": "福建省发改委",
      "publish_date": null,
      "crawl_date": "2026-03-16"
    },
    {
      "title": "福建省发展和改革委员会关于成品油价格调整的通告",
      "url": "http://fgw.fujian.gov.cn/zwgk/gsgg/../zfxxgkzl/zfxxgkml/yzdgkdqtxx/202511/t20251124_7037376.htm",
      "site_id": "fgw_fujian_gov_cn",
      "site_name": "福建省发改委",
      "publish_date": null,
      "crawl_date": "2026-03-16"
    },
    {
      "title": "福建省发展和改革委员会关于购买“宏观视野下探索建设两岸共同市场课题研究”项目询价结果的公告",
      "url": "http://fgw.fujian.gov.cn/202511/t20251124_7037151.htm",
      "site_id": "fgw_fujian_gov_cn",
      "site_name": "福建省发改委",
      "publish_date": null,
      "crawl_date": "2026-03-16"
    },
    {
      "title": "2025年省重点项目第二批“双随机、一公开”抽查情况公示",
      "url": "http://fgw.fujian.gov.cn/zwgk/gsgg/../ztzl/jgzf/ssjygk/202511/t20251112_7033298.htm",
      "site_id": "fgw_fujian_gov_cn",
      "site_name": "福建省发改委",
      "publish_date": null,
      "crawl_date": "2026-03-16"
    },
    {
      "title": "福建省发展和改革委员会关于购买“福建省‘十五五’构建优质高效服务业新体系课题研究”项目询价结果的公告",
      "url": "http://fgw.fujian.gov.cn/202511/t20251112_7033124.htm",
      "site_id": "fgw_fujian_gov_cn",
      "site_name": "福建省发改委",
      "publish_date": null,
      "crawl_date": "2026-03-16"
    },
    {
      "title": "福建省发展和改革委员会关于购买福建省“十五五”规划简明图集编制项目询价结果的公告",
      "url": "http://fgw.fujian.gov.cn/202511/t20251111_7032459.htm",
      "site_id": "fgw_fujian_gov_cn",
      "site_name": "福建省发改委",
      "publish_date": null,
      "crawl_date": "2026-03-16"
    },
    {
      "title": "福建省发展和改革委员会关于成品油价格调整的通告",
      "url": "http://fgw.fujian.gov.cn/zwgk/gsgg/../zfxxgkzl/zfxxgkml/yzdgkdqtxx/202511/t20251110_7032244.htm",
      "site_id": "fgw_fujian_gov_cn",
      "site_name": "福建省发改委",
      "publish_date": null,
      "crawl_date": "2026-03-16"
    },
    {
      "title": "福建省发展和改革委员会 国家能源局福建监管办公室关于福建省2025年新能源增量项目竞价有关事项的通知",
      "url": "http://fgw.fujian.gov.cn/zwgk/gsgg/../zfxxgkzl/zfxxgkml/yzdgkdqtxx/202511/t20251107_7031623.htm",
      "site_id": "fgw_fujian_gov_cn",
      "site_name": "福建省发改委",
      "publish_date": null,
      "crawl_date": "2026-03-16"
    },
    {
      "title": "福建省发展和改革委员会“双随机、一公开”抽查情况公示",
      "url": "http://fgw.fujian.gov.cn/zwgk/gsgg/../ztzl/jgzf/ssjygk/202511/t20251103_7029672.htm",
      "site_id": "fgw_fujian_gov_cn",
      "site_name": "福建省发改委",
      "publish_date": null,
      "crawl_date": "2026-03-16"
    },
    {
      "title": "福建省发展和改革委员会“双随机、一公开”抽查情况公示",
      "url": "http://fgw.fujian.gov.cn/zwgk/gsgg/../ztzl/jgzf/ssjygk/202510/t20251031_7028247.htm",
      "site_id": "fgw_fujian_gov_cn",
      "site_name": "福建省发改委",
      "publish_date": null,
      "crawl_date": "2026-03-16"
    },
    {
      "title": "福建省发展和改革委员会办公室关于购买“语音程控交换机设备维护”项目询价结果的公告",
      "url": "http://fgw.fujian.gov.cn/202510/t20251029_7027373.htm",
      "site_id": "fgw_fujian_gov_cn",
      "site_name": "福建省发改委",
      "publish_date": null,
      "crawl_date": "2026-03-16"
    },
    {
      "title": "关于2026年省级服务业发展引导专项资金项目的公示",
      "url": "http://fgw.fujian.gov.cn/202510/t20251027_7026610.htm",
      "site_id": "fgw_fujian_gov_cn",
      "site_name": "福建省发改委",
      "publish_date": null,
      "crawl_date": "2026-03-16"
    },
    {
      "title": "福建省发展和改革委员会关于成品油价格调整的通告",
      "url": "http://fgw.fujian.gov.cn/zwgk/gsgg/../zfxxgkzl/zfxxgkml/yzdgkdqtxx/202510/t20251027_7026572.htm",
      "site_id": "fgw_fujian_gov_cn",
      "site_name": "福建省发改委",
      "publish_date": null,
      "crawl_date": "2026-03-16"
    },
    {
      "title": "福建省发展和改革委员会关于购买福建省“十五五”产业转型升级思路项目询价结果的公告",
      "url": "http://fgw.fujian.gov.cn/202510/t20251027_7026560.htm",
      "site_id": "fgw_fujian_gov_cn",
      "site_name": "福建省发改委",
      "publish_date": null,
      "crawl_date": "2026-03-16"
    },
    {
      "title": "福建省发展和改革委员会“双随机、一公开”抽查情况公示",
      "url": "http://fgw.fujian.gov.cn/zwgk/gsgg/../ztzl/jgzf/ssjygk/202510/t20251016_7022027.htm",
      "site_id": "fgw_fujian_gov_cn",
      "site_name": "福建省发改委",
      "publish_date": null,
      "crawl_date": "2026-03-16"
    },
    {
      "title": "福建省发展和改革委员会关于成品油价格调整的通告",
      "url": "http://fgw.fujian.gov.cn/zwgk/gsgg/../zfxxgkzl/zfxxgkml/yzdgkdqtxx/202510/t20251013_7020867.htm",
      "site_id": "fgw_fujian_gov_cn",
      "site_name": "福建省发改委",
      "publish_date": null,
      "crawl_date": "2026-03-16"
    },
    {
      "title": "福建省发展和改革委员会关于做好2026年度省重点项目申报工作的函",
      "url": "http://fgw.fujian.gov.cn/zwgk/gsgg/../zfxxgkzl/zfxxgkml/yzdgkdqtxx/202509/t20250926_7015883.htm",
      "site_id": "fgw_fujian_gov_cn",
      "site_name": "福建省发改委",
      "publish_date": null,
      "crawl_date": "2026-03-16"
    },
    {
      "title": "福建省发展和改革委员会关于购买“福建省‘十五五’碳排放分析展望及预算管理课题研究”项目询价结果的公告",
      "url": "http://fgw.fujian.gov.cn/202509/t20250925_7014521.htm",
      "site_id": "fgw_fujian_gov_cn",
      "site_name": "福建省发改委",
      "publish_date": null,
      "crawl_date": "2026-03-16"
    },
    {
      "title": "询价结果公告",
      "url": "http://fgw.fujian.gov.cn/202509/t20250919_7012124.htm",
      "site_id": "fgw_fujian_gov_cn",
      "site_name": "福建省发改委",
      "publish_date": null,
      "crawl_date": "2026-03-16"
    },
    {
      "title": "关于2022—2024年省重点建设项目先进评选拟表彰对象的公示",
      "url": "http://fgw.fujian.gov.cn/202509/t20250917_7010847.htm",
      "site_id": "fgw_fujian_gov_cn",
      "site_name": "福建省发改委",
      "publish_date": null,
      "crawl_date": "2026-03-16"
    },
    {
      "title": "福建省发展和改革委员会关于购买福建省“十五五”“海上福建”建设专项规划编制询价结果的公告",
      "url": "http://fgw.fujian.gov.cn/202508/t20250827_6996549.htm",
      "site_id": "fgw_fujian_gov_cn",
      "site_name": "福建省发改委",
      "publish_date": null,
      "crawl_date": "2026-03-16"
    },
    {
      "title": "福建省发展和改革委员会关于成品油价格调整的通告",
      "url": "http://fgw.fujian.gov.cn/zwgk/gsgg/../zfxxgkzl/zfxxgkml/yzdgkdqtxx/202508/t20250826_6995886.htm",
      "site_id": "fgw_fujian_gov_cn",
      "site_name": "福建省发改委",
      "publish_date": null,
      "crawl_date": "2026-03-16"
    },
    {
      "title": "福建省发展和改革委员会涉企行政检查事项",
      "url": "http://fgw.fujian.gov.cn/202508/t20250818_6992812.htm",
      "site_id": "fgw_fujian_gov_cn",
      "site_name": "福建省发改委",
      "publish_date": null,
      "crawl_date": "2026-03-16"
    },
    {
      "title": "关于拟将厦门华夏国际电力发展有限公司 1、2号机组转为应急备用电源的公示",
      "url": "http://fgw.fujian.gov.cn/202508/t20250811_6989804.htm",
      "site_id": "fgw_fujian_gov_cn",
      "site_name": "福建省发改委",
      "publish_date": null,
      "crawl_date": "2026-03-16"
    },
    {
      "title": "福建省数字经济发展促进中心关于购买数字福建立法前期项目询价结果的公告",
      "url": "http://fgw.fujian.gov.cn/202508/t20250811_6989629.htm",
      "site_id": "fgw_fujian_gov_cn",
      "site_name": "福建省发改委",
      "publish_date": null,
      "crawl_date": "2026-03-16"
    },
    {
      "title": "关于召开《福建省促进数据产业高质量发展行动计划（2025-2027年）》征求意见座谈会的通知",
      "url": "http://fgw.fujian.gov.cn/202601/t20260105_7071710.htm",
      "site_id": "fgw_fujian_gov_cn",
      "site_name": "福建省发改委",
      "publish_date": null,
      "crawl_date": "2026-03-16"
    },
    {
      "title": "福建省发展和改革委员会关于购买“编制福建省市场准入效能评估报告”项目询价结果的公告",
      "url": "http://fgw.fujian.gov.cn/202508/t20250806_6988377.htm",
      "site_id": "fgw_fujian_gov_cn",
      "site_name": "福建省发改委",
      "publish_date": null,
      "crawl_date": "2026-03-16"
    },
    {
      "title": "福建省数据管理局关于公布2025年度全省数字经济核心产业创新企业名单的通知",
      "url": "http://fgw.fujian.gov.cn/202508/t20250801_6985427.htm",
      "site_id": "fgw_fujian_gov_cn",
      "site_name": "福建省发改委",
      "publish_date": null,
      "crawl_date": "2026-03-16"
    },
    {
      "title": "福建省发展和改革委员会关于购买 “‘十五五’数字福建专项前期项目”项目询价结果的公告",
      "url": "http://fgw.fujian.gov.cn/202507/t20250731_6977030.htm",
      "site_id": "fgw_fujian_gov_cn",
      "site_name": "福建省发改委",
      "publish_date": null,
      "crawl_date": "2026-03-16"
    },
    {
      "title": "福建省发展和改革委员会关于公布截至2025年6月底全省建设生产煤矿产能和瓦斯等级的通知",
      "url": "http://fgw.fujian.gov.cn/zwgk/gsgg/../zfxxgkzl/zfxxgkml/yzdgkdqtxx/202507/t20250723_6970134.htm",
      "site_id": "fgw_fujian_gov_cn",
      "site_name": "福建省发改委",
      "publish_date": null,
      "crawl_date": "2026-03-16"
    },
    {
      "title": "福建省发展和改革委员会政府法律顾问服务询价中标公告",
      "url": "http://fgw.fujian.gov.cn/202507/t20250722_6969810.htm",
      "site_id": "fgw_fujian_gov_cn",
      "site_name": "福建省发改委",
      "publish_date": null,
      "crawl_date": "2026-03-16"
    },
    {
      "title": "福建省政府定价的殡葬服务收费文件目录",
      "url": "http://fgw.fujian.gov.cn/202507/t20250721_6969463.htm",
      "site_id": "fgw_fujian_gov_cn",
      "site_name": "福建省发改委",
      "publish_date": null,
      "crawl_date": "2026-03-16"
    },
    {
      "title": "福建省发展和改革委员会关于购买“福建省‘十五五’更高水平更高质量做好节能工作课题研究”项目询价结果的公告",
      "url": "http://fgw.fujian.gov.cn/202507/t20250721_6969444.htm",
      "site_id": "fgw_fujian_gov_cn",
      "site_name": "福建省发改委",
      "publish_date": null,
      "crawl_date": "2026-03-16"
    },
    {
      "title": "福建省发展和改革委员会关于征集福建省政务服务标准化技术委员会委员的公告",
      "url": "http://fgw.fujian.gov.cn/202507/t20250721_6969420.htm",
      "site_id": "fgw_fujian_gov_cn",
      "site_name": "福建省发改委",
      "publish_date": null,
      "crawl_date": "2026-03-16"
    },
    {
      "title": "福建省发展和改革委员会“双随机、一公开”抽查情况公示",
      "url": "http://fgw.fujian.gov.cn/zwgk/gsgg/../ztzl/jgzf/ssjygk/202507/t20250718_6968787.htm",
      "site_id": "fgw_fujian_gov_cn",
      "site_name": "福建省发改委",
      "publish_date": null,
      "crawl_date": "2026-03-16"
    },
    {
      "title": "2025年福建省民营企业感知度问卷调查",
      "url": "http://fgw.fujian.gov.cn/202507/t20250717_6968272.htm",
      "site_id": "fgw_fujian_gov_cn",
      "site_name": "福建省发改委",
      "publish_date": null,
      "crawl_date": "2026-03-16"
    },
    {
      "title": "询价结果公告",
      "url": "http://fgw.fujian.gov.cn/202507/t20250716_6967955.htm",
      "site_id": "fgw_fujian_gov_cn",
      "site_name": "福建省发改委",
      "publish_date": null,
      "crawl_date": "2026-03-16"
    },
    {
      "title": "福建省数据管理局关于征集第四届福建省信息化标准化技术委员会委员的通知",
      "url": "http://fgw.fujian.gov.cn/202507/t20250716_6967932.htm",
      "site_id": "fgw_fujian_gov_cn",
      "site_name": "福建省发改委",
      "publish_date": null,
      "crawl_date": "2026-03-16"
    },
    {
      "title": "福建省发展和改革委员会关于成品油价格调整的通告",
      "url": "http://fgw.fujian.gov.cn/zwgk/gsgg/../zfxxgkzl/zfxxgkml/yzdgkdqtxx/202507/t20250715_6967533.htm",
      "site_id": "fgw_fujian_gov_cn",
      "site_name": "福建省发改委",
      "publish_date": null,
      "crawl_date": "2026-03-16"
    },
    {
      "title": "福建省数据管理局关于福建省首批人工智能行业高质量数据集补充名单的公示",
      "url": "http://fgw.fujian.gov.cn/202507/t20250703_6961020.htm",
      "site_id": "fgw_fujian_gov_cn",
      "site_name": "福建省发改委",
      "publish_date": null,
      "crawl_date": "2026-03-16"
    },
    {
      "title": "福建省发展和改革委员会关于成品油价格调整的通告",
      "url": "http://fgw.fujian.gov.cn/zwgk/gsgg/../zfxxgkzl/zfxxgkml/yzdgkdqtxx/202507/t20250701_6960534.htm",
      "site_id": "fgw_fujian_gov_cn",
      "site_name": "福建省发改委",
      "publish_date": null,
      "crawl_date": "2026-03-16"
    },
    {
      "title": "福建省发展和改革委员会关于购买“福建省“十四五”园区循环化改造成效评估”项目询价结果的公告",
      "url": "http://fgw.fujian.gov.cn/202507/t20250701_6960488.htm",
      "site_id": "fgw_fujian_gov_cn",
      "site_name": "福建省发改委",
      "publish_date": null,
      "crawl_date": "2026-03-16"
    },
    {
      "title": "福建省数据管理局关于2025年度福建省数字经济核心产业创新企业征集遴选结果的公示",
      "url": "http://fgw.fujian.gov.cn/202506/t20250630_6959191.htm",
      "site_id": "fgw_fujian_gov_cn",
      "site_name": "福建省发改委",
      "publish_date": null,
      "crawl_date": "2026-03-16"
    },
    {
      "title": "福建省发展和改革委员会关于购买“基于‘电－碳分析模型’省级碳排放分析研究”项目询价结果的公告",
      "url": "http://fgw.fujian.gov.cn/202506/t20250620_6930015.htm",
      "site_id": "fgw_fujian_gov_cn",
      "site_name": "福建省发改委",
      "publish_date": null,
      "crawl_date": "2026-03-16"
    },
    {
      "title": "2025年度学习贯彻习近平新时代中国特色社会主义思想重点课题承担单位遴选结果公告",
      "url": "http://fgw.fujian.gov.cn/202506/t20250618_6928881.htm",
      "site_id": "fgw_fujian_gov_cn",
      "site_name": "福建省发改委",
      "publish_date": null,
      "crawl_date": "2026-03-16"
    },
    {
      "title": "福建省发展和改革委员会关于成品油价格调整的通告",
      "url": "http://fgw.fujian.gov.cn/zwgk/gsgg/../zfxxgkzl/zfxxgkml/yzdgkdqtxx/202506/t20250617_6928392.htm",
      "site_id": "fgw_fujian_gov_cn",
      "site_name": "福建省发改委",
      "publish_date": null,
      "crawl_date": "2026-03-16"
    },
    {
      "title": "关于公开征求《福建省发展和改革委员会关于做好<分布式光伏发电开发建设管理办法>实施工作的通知（征求意见稿）》意见建议的公告",
      "url": "http://fgw.fujian.gov.cn/202506/t20250617_6928106.htm",
      "site_id": "fgw_fujian_gov_cn",
      "site_name": "福建省发改委",
      "publish_date": null,
      "crawl_date": "2026-03-16"
    },
    {
      "title": "福建省发展和改革委员会关于购买“福建省‘十五五’时期重大问题补充课题研究” 项目询价结果的公告",
      "url": "http://fgw.fujian.gov.cn/202506/t20250617_6928095.htm",
      "site_id": "fgw_fujian_gov_cn",
      "site_name": "福建省发改委",
      "publish_date": null,
      "crawl_date": "2026-03-16"
    },
    {
      "title": "福建省发展和改革委员会关于购买“福建省‘十五五’生态省建设专项规划课题研究”项目询价结果的公告",
      "url": "http://fgw.fujian.gov.cn/202506/t20250613_6927060.htm",
      "site_id": "fgw_fujian_gov_cn",
      "site_name": "福建省发改委",
      "publish_date": null,
      "crawl_date": "2026-03-16"
    },
    {
      "title": "国家发展改革委",
      "url": "https://www.ndrc.gov.cn/",
      "site_id": "fgw_fujian_gov_cn",
      "site_name": "福建省发改委",
      "publish_date": null,
      "crawl_date": "2026-03-16"
    },
    {
      "title": "国家发展改革委",
      "url": "https://www.ndrc.gov.cn/",
      "site_id": "fgw_fujian_gov_cn",
      "site_name": "福建省发改委",
      "publish_date": null,
      "crawl_date": "2026-03-16"
    },
    {
      "title": "北京发展改革委",
      "url": "http://fgw.beijing.gov.cn",
      "site_id": "fgw_fujian_gov_cn",
      "site_name": "福建省发改委",
      "publish_date": null,
      "crawl_date": "2026-03-16"
    },
    {
      "title": "安徽省发展改革委",
      "url": "http://fzggw.ah.gov.cn",
      "site_id": "fgw_fujian_gov_cn",
      "site_name": "福建省发改委",
      "publish_date": null,
      "crawl_date": "2026-03-16"
    },
    {
      "title": "天津市发展改革委",
      "url": "http://fzgg.tj.gov.cn",
      "site_id": "fgw_fujian_gov_cn",
      "site_name": "福建省发改委",
      "publish_date": null,
      "crawl_date": "2026-03-16"
    },
    {
      "title": "重庆市发展改革委",
      "url": "http://fzggw.cq.gov.cn",
      "site_id": "fgw_fujian_gov_cn",
      "site_name": "福建省发改委",
      "publish_date": null,
      "crawl_date": "2026-03-16"
    },
    {
      "title": "河北省发展改革委",
      "url": "https://hbdrc.hebei.gov.cn/",
      "site_id": "fgw_fujian_gov_cn",
      "site_name": "福建省发改委",
      "publish_date": null,
      "crawl_date": "2026-03-16"
    },
    {
      "title": "四川省发展改革委",
      "url": "http://fgw.sc.gov.cn",
      "site_id": "fgw_fujian_gov_cn",
      "site_name": "福建省发改委",
      "publish_date": null,
      "crawl_date": "2026-03-16"
    },
    {
      "title": "福建省发展改革委",
      "url": "http://fgw.fujian.gov.cn",
      "site_id": "fgw_fujian_gov_cn",
      "site_name": "福建省发改委",
      "publish_date": null,
      "crawl_date": "2026-03-16"
    },
    {
      "title": "山西省发展改革委",
      "url": "http://fgw.shanxi.gov.cn/",
      "site_id": "fgw_fujian_gov_cn",
      "site_name": "福建省发改委",
      "publish_date": null,
      "crawl_date": "2026-03-16"
    },
    {
      "title": "贵州省发展改革委",
      "url": "http://fgw.guizhou.gov.cn",
      "site_id": "fgw_fujian_gov_cn",
      "site_name": "福建省发改委",
      "publish_date": null,
      "crawl_date": "2026-03-16"
    },
    {
      "title": "江西省发展改革委",
      "url": "http://drc.jiangxi.gov.cn",
      "site_id": "fgw_fujian_gov_cn",
      "site_name": "福建省发改委",
      "publish_date": null,
      "crawl_date": "2026-03-16"
    },
    {
      "title": "内蒙古自治区发展改革委",
      "url": "http://www.nmg.gov.cn",
      "site_id": "fgw_fujian_gov_cn",
      "site_name": "福建省发改委",
      "publish_date": null,
      "crawl_date": "2026-03-16"
    },
    {
      "title": "云南省发展改革委",
      "url": "http://yndrc.yn.gov.cn",
      "site_id": "fgw_fujian_gov_cn",
      "site_name": "福建省发改委",
      "publish_date": null,
      "crawl_date": "2026-03-16"
    },
    {
      "title": "山东省发展改革委",
      "url": "http://fgw.shandong.gov.cn/",
      "site_id": "fgw_fujian_gov_cn",
      "site_name": "福建省发改委",
      "publish_date": null,
      "crawl_date": "2026-03-16"
    },
    {
      "title": "辽宁省发展改革委",
      "url": "http://fgw.ln.gov.cn",
      "site_id": "fgw_fujian_gov_cn",
      "site_name": "福建省发改委",
      "publish_date": null,
      "crawl_date": "2026-03-16"
    },
    {
      "title": "西藏自治区发展改革委",
      "url": "http://drc.xizang.gov.cn",
      "site_id": "fgw_fujian_gov_cn",
      "site_name": "福建省发改委",
      "publish_date": null,
      "crawl_date": "2026-03-16"
    },
    {
      "title": "河南省发展改革委",
      "url": "https://fgw.henan.gov.cn/",
      "site_id": "fgw_fujian_gov_cn",
      "site_name": "福建省发改委",
      "publish_date": null,
      "crawl_date": "2026-03-16"
    },
    {
      "title": "湖北省发展改革委",
      "url": "http://fgw.hubei.gov.cn",
      "site_id": "fgw_fujian_gov_cn",
      "site_name": "福建省发改委",
      "publish_date": null,
      "crawl_date": "2026-03-16"
    },
    {
      "title": "吉林省发展改革委",
      "url": "http://jldrc.jl.gov.cn",
      "site_id": "fgw_fujian_gov_cn",
      "site_name": "福建省发改委",
      "publish_date": null,
      "crawl_date": "2026-03-16"
    },
    {
      "title": "陕西省发展改革委",
      "url": "http://sndrc.shaanxi.gov.cn",
      "site_id": "fgw_fujian_gov_cn",
      "site_name": "福建省发改委",
      "publish_date": null,
      "crawl_date": "2026-03-16"
    },
    {
      "title": "黑龙江省发展改革委",
      "url": "http://drc.hlj.gov.cn/",
      "site_id": "fgw_fujian_gov_cn",
      "site_name": "福建省发改委",
      "publish_date": null,
      "crawl_date": "2026-03-16"
    },
    {
      "title": "甘肃省发展改革委",
      "url": "http://fzgg.gansu.gov.cn",
      "site_id": "fgw_fujian_gov_cn",
      "site_name": "福建省发改委",
      "publish_date": null,
      "crawl_date": "2026-03-16"
    },
    {
      "title": "湖南省发展改革委",
      "url": "http://fgw.hunan.gov.cn",
      "site_id": "fgw_fujian_gov_cn",
      "site_name": "福建省发改委",
      "publish_date": null,
      "crawl_date": "2026-03-16"
    },
    {
      "title": "上海市发展改革委",
      "url": "http://fgw.sh.gov.cn",
      "site_id": "fgw_fujian_gov_cn",
      "site_name": "福建省发改委",
      "publish_date": null,
      "crawl_date": "2026-03-16"
    },
    {
      "title": "广东省发展改革委",
      "url": "http://drc.gd.gov.cn",
      "site_id": "fgw_fujian_gov_cn",
      "site_name": "福建省发改委",
      "publish_date": null,
      "crawl_date": "2026-03-16"
    },
    {
      "title": "青海省发展改革委",
      "url": "http://fgw.qinghai.gov.cn",
      "site_id": "fgw_fujian_gov_cn",
      "site_name": "福建省发改委",
      "publish_date": null,
      "crawl_date": "2026-03-16"
    },
    {
      "title": "宁夏自治区发展改革委",
      "url": "http://fzggw.nx.gov.cn",
      "site_id": "fgw_fujian_gov_cn",
      "site_name": "福建省发改委",
      "publish_date": null,
      "crawl_date": "2026-03-16"
    },
    {
      "title": "广西自治区发展改革委",
      "url": "http://fgw.gxzf.gov.cn",
      "site_id": "fgw_fujian_gov_cn",
      "site_name": "福建省发改委",
      "publish_date": null,
      "crawl_date": "2026-03-16"
    },
    {
      "title": "江苏省发展改革委",
      "url": "http://fzggw.jiangsu.gov.cn/",
      "site_id": "fgw_fujian_gov_cn",
      "site_name": "福建省发改委",
      "publish_date": null,
      "crawl_date": "2026-03-16"
    },
    {
      "title": "浙江省发展改革委",
      "url": "http://fzggw.zj.gov.cn",
      "site_id": "fgw_fujian_gov_cn",
      "site_name": "福建省发改委",
      "publish_date": null,
      "crawl_date": "2026-03-16"
    },
    {
      "title": "新疆自治区发展改革委",
      "url": "http://xjdrc.xinjiang.gov.cn/",
      "site_id": "fgw_fujian_gov_cn",
      "site_name": "福建省发改委",
      "publish_date": null,
      "crawl_date": "2026-03-16"
    },
    {
      "title": "海南省发展改革委",
      "url": "http://plan.hainan.gov.cn",
      "site_id": "fgw_fujian_gov_cn",
      "site_name": "福建省发改委",
      "publish_date": null,
      "crawl_date": "2026-03-16"
    },
    {
      "title": "福州市发改委",
      "url": "http://fgw.fuzhou.gov.cn",
      "site_id": "fgw_fujian_gov_cn",
      "site_name": "福建省发改委",
      "publish_date": null,
      "crawl_date": "2026-03-16"
    },
    {
      "title": "福州市发改委",
      "url": "http://fgw.fuzhou.gov.cn",
      "site_id": "fgw_fujian_gov_cn",
      "site_name": "福建省发改委",
      "publish_date": null,
      "crawl_date": "2026-03-16"
    },
    {
      "title": "厦门市发改委",
      "url": "http://dpc.xm.gov.cn/",
      "site_id": "fgw_fujian_gov_cn",
      "site_name": "福建省发改委",
      "publish_date": null,
      "crawl_date": "2026-03-16"
    },
    {
      "title": "漳州市发改委",
      "url": "http://fgw.zhangzhou.gov.cn/",
      "site_id": "fgw_fujian_gov_cn",
      "site_name": "福建省发改委",
      "publish_date": null,
      "crawl_date": "2026-03-16"
    },
    {
      "title": "泉州市发改委",
      "url": "http://fgw.quanzhou.gov.cn/",
      "site_id": "fgw_fujian_gov_cn",
      "site_name": "福建省发改委",
      "publish_date": null,
      "crawl_date": "2026-03-16"
    },
    {
      "title": "三明市发改委",
      "url": "http://fgw.sm.gov.cn",
      "site_id": "fgw_fujian_gov_cn",
      "site_name": "福建省发改委",
      "publish_date": null,
      "crawl_date": "2026-03-16"
    },
    {
      "title": "莆田市发改委",
      "url": "http://fgw.putian.gov.cn",
      "site_id": "fgw_fujian_gov_cn",
      "site_name": "福建省发改委",
      "publish_date": null,
      "crawl_date": "2026-03-16"
    },
    {
      "title": "南平市发改委",
      "url": "http://fgw.np.gov.cn/",
      "site_id": "fgw_fujian_gov_cn",
      "site_name": "福建省发改委",
      "publish_date": null,
      "crawl_date": "2026-03-16"
    },
    {
      "title": "龙岩市发改委",
      "url": "http://fgw.longyan.gov.cn/",
      "site_id": "fgw_fujian_gov_cn",
      "site_name": "福建省发改委",
      "publish_date": null,
      "crawl_date": "2026-03-16"
    },
    {
      "title": "宁德市发改委",
      "url": "http://fgw.ningde.gov.cn/",
      "site_id": "fgw_fujian_gov_cn",
      "site_name": "福建省发改委",
      "publish_date": null,
      "crawl_date": "2026-03-16"
    },
    {
      "title": "平潭综合实验区",
      "url": "http://www.pingtan.gov.cn/",
      "site_id": "fgw_fujian_gov_cn",
      "site_name": "福建省发改委",
      "publish_date": null,
      "crawl_date": "2026-03-16"
    },
    {
      "title": "省民族宗教厅",
      "url": "http://mzzjt.fujian.gov.cn/",
      "site_id": "fgw_fujian_gov_cn",
      "site_name": "福建省发改委",
      "publish_date": null,
      "crawl_date": "2026-03-16"
    },
    {
      "title": "省自然资源厅",
      "url": "http://zrzyt.fujian.gov.cn",
      "site_id": "fgw_fujian_gov_cn",
      "site_name": "福建省发改委",
      "publish_date": null,
      "crawl_date": "2026-03-16"
    },
    {
      "title": "省生态环境厅",
      "url": "http://sthjt.fujian.gov.cn",
      "site_id": "fgw_fujian_gov_cn",
      "site_name": "福建省发改委",
      "publish_date": null,
      "crawl_date": "2026-03-16"
    },
    {
      "title": "省交通运输厅",
      "url": "http://jtyst.fujian.gov.cn/",
      "site_id": "fgw_fujian_gov_cn",
      "site_name": "福建省发改委",
      "publish_date": null,
      "crawl_date": "2026-03-16"
    },
    {
      "title": "省农业农村厅",
      "url": "http://nynct.fujian.gov.cn/",
      "site_id": "fgw_fujian_gov_cn",
      "site_name": "福建省发改委",
      "publish_date": null,
      "crawl_date": "2026-03-16"
    },
    {
      "title": "省退役军人厅",
      "url": "http://tyjrswt.fujian.gov.cn/",
      "site_id": "fgw_fujian_gov_cn",
      "site_name": "福建省发改委",
      "publish_date": null,
      "crawl_date": "2026-03-16"
    },
    {
      "title": "省海洋渔业局",
      "url": "http://hyyyj.fujian.gov.cn/",
      "site_id": "fgw_fujian_gov_cn",
      "site_name": "福建省发改委",
      "publish_date": null,
      "crawl_date": "2026-03-16"
    },
    {
      "title": "省市场监管局",
      "url": "http://scjgj.fujian.gov.cn/",
      "site_id": "fgw_fujian_gov_cn",
      "site_name": "福建省发改委",
      "publish_date": null,
      "crawl_date": "2026-03-16"
    },
    {
      "title": "省机关管理局",
      "url": "http://jgswglj.fujian.gov.cn/",
      "site_id": "fgw_fujian_gov_cn",
      "site_name": "福建省发改委",
      "publish_date": null,
      "crawl_date": "2026-03-16"
    },
    {
      "title": "闽政通App",
      "url": "javascript:;",
      "site_id": "fgw_fujian_gov_cn",
      "site_name": "福建省发改委",
      "publish_date": null,
      "crawl_date": "2026-03-16"
    }
  ]
}